{
  "date": "2026-04-25",
  "title": "金融日报 2026-04-25",
  "summary": "央行MLF缩量续作回笼中期流动性；美债清算配套继续推进；美国消费者信心与通胀预期恶化。",
  "notion_url": "https://www.notion.so/34df9553c5708108a7a2da1dd9083f08",
  "reportMarkdown": "## 今日重点\n\n- 【宏观经济】央行MLF缩量续作并净回笼：中期流动性边际趋紧，关注资金利率与同业存单定价。\n- 【宏观经济】美国消费者信心终值创阶段低位且通胀预期跳升：强化“增长走弱/通胀偏高”两难。\n- 【监管政策】SEC批准美债客户交叉保证金：Treasury clearing配套推进，有利于保证金效率与流动性韧性。\n\n## 宏观与政策\n\n- 【宏观经济】中国人民银行公告4月27日开展4000亿元1年期MLF；当月到期6000亿元，MLF净回笼2000亿元。\n- 【宏观经济】密歇根大学4月消费者信心终值49.8；1年通胀预期升至4.7%，长期预期升至3.5%。\n\n## 市场动态\n\n- 推断：在“通胀预期抬升+流动性边际收敛”的组合下，利率波动可能上升，风险资产更依赖盈利兑现与现金流质量。\n\n## 金融机构与监管\n\n- 【监管政策】SEC豁免令+规则变更允许美债现券×期货在客户层面交叉保证金（FICC×CME），推进Treasury clearing实施。\n- 【监管政策】SEC对CAT等审计轨迹开展概念性征求意见，议题集中在成本分摊、治理、数据范围、隐私与网络安全。\n- 【金融机构】美国区域银行并购：United Community Banks拟并购Peach State，关注监管审批与整合进度。\n\n## 风险提示\n\n- 消费者信心下行且通胀预期抬升：若传导至工资/定价行为，可能延长高利率环境并压制估值中枢。\n- 交叉保证金与清算改革提升效率的同时也增强跨市场联动，极端波动下保证金与流动性安排仍需检验。\n- 大宗品价格高位叠加供给扰动（如矿山爬坡调整）可能放大通胀与企业利润分化。\n\n## 后续观察点\n\n1. 4月27日MLF实际中标利率与超额认购情况，以及后续买断式逆回购/OMO对冲节奏。\n2. 密歇根通胀预期上行是否在后续数据中延续，并对FOMC路径预期产生实质影响。\n3. 美债客户交叉保证金的准入条件、参与者准备与落地时间表（SEC/CFTC/FICC/CME）。\n4. CAT概念性征求意见的反馈分歧与后续规则走向（成本、隐私、网络安全、治理结构）。\n5. 区域银行并购潮是否扩散至更多标的，以及监管审批口径变化。\n6. 铜矿供给侧（Grasberg爬坡）调整对2026年铜供需预期与资源股波动的影响。\n\n## JSON\n\n```json\n[\n  {\n    \"title\": \"中国人民银行公告：4月27日开展4000亿元1年期MLF（当月净回笼2000亿）\",\n    \"date\": \"2026-04-24\",\n    \"source\": \"中国人民银行\",\n    \"category\": \"宏观经济\",\n    \"importance\": \"高\",\n    \"summary\": \"4月MLF缩量续作，净回笼2000亿元\",\n    \"impact\": \"央行公告4月27日开展4000亿元1年期MLF；结合当月到期规模6000亿元，意味着4月MLF净回笼2000亿元。对银行体系中期流动性的边际支持减弱，短端资金利率与同业存单定价可能更依赖买断式逆回购与公开市场节奏，收益率曲线的“过度下行”空间受限。\",\n    \"targets\": \"银行体系中期流动性、DR/同业存单利率、债券收益率曲线、信用利差\",\n    \"direction\": \"中性\",\n    \"keywords\": [\n      \"中国人民银行\",\n      \"MLF\",\n      \"流动性\",\n      \"银行间市场\",\n      \"同业存单\"\n    ],\n    \"follow_up\": \"是\",\n    \"link\": \"https://finance.people.com.cn/n1/2026/0424/c1004-40708345.html\"\n  },\n  {\n    \"title\": \"美国密歇根大学4月消费者信心终值49.8，通胀预期跳升\",\n    \"date\": \"2026-04-24\",\n    \"source\": \"University of Michigan\",\n    \"category\": \"宏观经济\",\n    \"importance\": \"高\",\n    \"summary\": \"4月信心终值49.8，1年通胀预期升至4.7%\",\n    \"impact\": \"密歇根大学“Surveys of Consumers”显示4月消费者信心指数终值49.8，显著低于3月；1年期通胀预期从3.8%升至4.7%，长期通胀预期升至3.5%。这类“信心走弱+通胀预期抬升”的组合会加大货币政策预期分歧：一方面抑制风险偏好并拖累可选消费预期，另一方面强化通胀黏性担忧，可能推升期限溢价与美元利率波动。\",\n    \"targets\": \"美联储政策预期、美元利率曲线、风险资产情绪、可选消费板块\",\n    \"direction\": \"利空\",\n    \"keywords\": [\n      \"美国\",\n      \"消费者信心\",\n      \"通胀预期\",\n      \"密歇根大学\",\n      \"利率\"\n    ],\n    \"follow_up\": \"是\",\n    \"link\": \"https://www.sca.isr.umich.edu/\"\n  },\n  {\n    \"title\": \"SEC批准美债客户交叉保证金（FICC×CME）配套豁免与规则变更\",\n    \"date\": \"2026-04-15\",\n    \"source\": \"SEC\",\n    \"category\": \"监管政策\",\n    \"importance\": \"高\",\n    \"summary\": \"美债现券×期货客户交叉保证金获批\",\n    \"impact\": \"SEC发布有条件豁免令，允许在满足条件下将FICC清算的现金美债头寸与CME清算的美债期货头寸在客户层面开展交叉保证金，并同步批准FICC规则变更以纳入与CME的交叉保证金协议扩展。该举措提升保证金效率、释放做市与回购链条的资金周转能力，属于Treasury clearing实施的重要配套，边际有利于美债市场流动性与韧性。\",\n    \"targets\": \"美国国债现券（FICC）、国债期货（CME）、做市商/经纪商/FCM、保证金与流动性管理\",\n    \"direction\": \"利多\",\n    \"keywords\": [\n      \"SEC\",\n      \"CFTC\",\n      \"美债\",\n      \"FICC\",\n      \"CME\",\n      \"交叉保证金\"\n    ],\n    \"follow_up\": \"是\",\n    \"link\": \"https://www.sec.gov/newsroom/press-releases/2026-36-sec-approves-exemptive-order-proposed-rule-change-permit-customer-cross-margining-us-treasury-market\"\n  },\n  {\n    \"title\": \"SEC就CAT等审计轨迹与数据源发起概念性征求意见（34-105251）\",\n    \"date\": \"2026-04-16\",\n    \"source\": \"SEC\",\n    \"category\": \"监管政策\",\n    \"importance\": \"中\",\n    \"summary\": \"SEC对CAT“基础性/存在性”问题征求意见\",\n    \"impact\": \"SEC发布概念性征求意见，对Consolidated Audit Trail（CAT）及其他审计轨迹/数据源进行全面评估，重点覆盖资金与成本管理、治理结构、数据范围设计、网络安全与数据隐私，以及监管需要与公民隐私之间的平衡。该过程为后续规则重构打开窗口，可能影响券商/交易所/市场参与者的数据报送成本与合规边界。\",\n    \"targets\": \"美国证券市场数据基础设施、券商/交易所合规成本、隐私与网络安全治理\",\n    \"direction\": \"中性\",\n    \"keywords\": [\n      \"SEC\",\n      \"CAT\",\n      \"审计轨迹\",\n      \"市场数据\",\n      \"隐私\",\n      \"网络安全\"\n    ],\n    \"follow_up\": \"是\",\n    \"link\": \"https://www.sec.gov/newsroom/press-releases/2026-37-sec-seeks-public-comment-consolidated-audit-trail-other-audit-trails-data-sources\"\n  },\n  {\n    \"title\": \"United Community Banks宣布与Peach State Bancshares签署并购协议\",\n    \"date\": \"2026-04-21\",\n    \"source\": \"SEC\",\n    \"category\": \"金融机构\",\n    \"importance\": \"中\",\n    \"summary\": \"美国区域银行并购再现：UCB收购Peach State\",\n    \"impact\": \"United Community Banks披露将并购Peach State Bancshares，并在交易完成后推动双方银行主体合并。区域/社区银行并购有助于扩张存贷规模与网点覆盖，同时也反映行业在资本与成本约束下的整合趋势；对同业竞争格局与当地存款定价具有边际影响。\",\n    \"targets\": \"美国区域/社区银行行业、并购整合风险、当地存款与信贷竞争\",\n    \"direction\": \"中性\",\n    \"keywords\": [\n      \"区域银行\",\n      \"并购\",\n      \"UCB\",\n      \"Peach State\",\n      \"美国银行业\"\n    ],\n    \"follow_up\": \"是\",\n    \"link\": \"https://www.sec.gov/Archives/edgar/data/857855/000110465926045711/tm2612284d1_8k.htm\"\n  },\n  {\n    \"title\": \"Freeport-McMoRan公布2026年Q1业绩并调整Grasberg Block Cave爬坡节奏\",\n    \"date\": \"2026-04-23\",\n    \"source\": \"Freeport-McMoRan\",\n    \"category\": \"重点公司\",\n    \"importance\": \"中\",\n    \"summary\": \"FCX Q1净利8.81亿美元；Grasberg爬坡节奏调整影响全年销量指引\",\n    \"impact\": \"FCX披露2026年Q1归母净利润8.81亿美元（调整后8.30亿美元），并在高铜价/高金价环境下现金流表现稳健；同时因Grasberg Block Cave地下矿物料处理系统调整，全年铜/金销量指引下调主要反映爬坡时点调整。该信息同时影响铜矿供给预期与矿企成本/资本开支路径，对铜价波动与资源股风险偏好具有参考价值。\",\n    \"targets\": \"铜/金商品价格预期、铜矿供给与成本曲线、资源股（铜矿/金矿）估值\",\n    \"direction\": \"中性\",\n    \"keywords\": [\n      \"FCX\",\n      \"铜\",\n      \"黄金\",\n      \"Grasberg\",\n      \"业绩\",\n      \"指引\"\n    ],\n    \"follow_up\": \"是\",\n    \"link\": \"https://www.sec.gov/Archives/edgar/data/831259/000083125926000021/a1q2026exhibit991.htm\"\n  }\n]\n```",
  "events": [
    {
      "title": "中国人民银行公告：4月27日开展4000亿元1年期MLF（当月净回笼2000亿）",
      "date": "2026-04-24",
      "source": "中国人民银行",
      "category": "宏观经济",
      "importance": "高",
      "summary": "4月MLF缩量续作，净回笼2000亿元",
      "impact": "央行公告4月27日开展4000亿元1年期MLF；结合当月到期规模6000亿元，意味着4月MLF净回笼2000亿元。对银行体系中期流动性的边际支持减弱，短端资金利率与同业存单定价可能更依赖买断式逆回购与公开市场节奏，收益率曲线的“过度下行”空间受限。",
      "targets": "银行体系中期流动性、DR/同业存单利率、债券收益率曲线、信用利差",
      "direction": "中性",
      "keywords": [
        "中国人民银行",
        "MLF",
        "流动性",
        "银行间市场",
        "同业存单"
      ],
      "follow_up": "是",
      "link": "https://finance.people.com.cn/n1/2026/0424/c1004-40708345.html",
      "notion_url": "https://www.notion.so/34df9553c57081bd9993ff96604c7d4a"
    },
    {
      "title": "美国密歇根大学4月消费者信心终值49.8，通胀预期跳升",
      "date": "2026-04-24",
      "source": "University of Michigan",
      "category": "宏观经济",
      "importance": "高",
      "summary": "4月信心终值49.8，1年通胀预期升至4.7%",
      "impact": "密歇根大学“Surveys of Consumers”显示4月消费者信心指数终值49.8，显著低于3月；1年期通胀预期从3.8%升至4.7%，长期通胀预期升至3.5%。这类“信心走弱+通胀预期抬升”的组合会加大货币政策预期分歧：一方面抑制风险偏好并拖累可选消费预期，另一方面强化通胀黏性担忧，可能推升期限溢价与美元利率波动。",
      "targets": "美联储政策预期、美元利率曲线、风险资产情绪、可选消费板块",
      "direction": "利空",
      "keywords": [
        "美国",
        "消费者信心",
        "通胀预期",
        "密歇根大学",
        "利率"
      ],
      "follow_up": "是",
      "link": "https://www.sca.isr.umich.edu/",
      "notion_url": "https://www.notion.so/34df9553c57081ceb771f0db0ce171e5"
    },
    {
      "title": "SEC批准美债客户交叉保证金（FICC×CME）配套豁免与规则变更",
      "date": "2026-04-15",
      "source": "SEC",
      "category": "监管政策",
      "importance": "高",
      "summary": "美债现券×期货客户交叉保证金获批",
      "impact": "SEC发布有条件豁免令，允许在满足条件下将FICC清算的现金美债头寸与CME清算的美债期货头寸在客户层面开展交叉保证金，并同步批准FICC规则变更以纳入与CME的交叉保证金协议扩展。该举措提升保证金效率、释放做市与回购链条的资金周转能力，属于Treasury clearing实施的重要配套，边际有利于美债市场流动性与韧性。",
      "targets": "美国国债现券（FICC）、国债期货（CME）、做市商/经纪商/FCM、保证金与流动性管理",
      "direction": "利多",
      "keywords": [
        "SEC",
        "CFTC",
        "美债",
        "FICC",
        "CME",
        "交叉保证金"
      ],
      "follow_up": "是",
      "link": "https://www.sec.gov/newsroom/press-releases/2026-36-sec-approves-exemptive-order-proposed-rule-change-permit-customer-cross-margining-us-treasury-market",
      "notion_url": "https://www.notion.so/34df9553c5708147ab76cb69bcdd4844"
    },
    {
      "title": "SEC就CAT等审计轨迹与数据源发起概念性征求意见（34-105251）",
      "date": "2026-04-16",
      "source": "SEC",
      "category": "监管政策",
      "importance": "中",
      "summary": "SEC对CAT“基础性/存在性”问题征求意见",
      "impact": "SEC发布概念性征求意见，对Consolidated Audit Trail（CAT）及其他审计轨迹/数据源进行全面评估，重点覆盖资金与成本管理、治理结构、数据范围设计、网络安全与数据隐私，以及监管需要与公民隐私之间的平衡。该过程为后续规则重构打开窗口，可能影响券商/交易所/市场参与者的数据报送成本与合规边界。",
      "targets": "美国证券市场数据基础设施、券商/交易所合规成本、隐私与网络安全治理",
      "direction": "中性",
      "keywords": [
        "SEC",
        "CAT",
        "审计轨迹",
        "市场数据",
        "隐私",
        "网络安全"
      ],
      "follow_up": "是",
      "link": "https://www.sec.gov/newsroom/press-releases/2026-37-sec-seeks-public-comment-consolidated-audit-trail-other-audit-trails-data-sources",
      "notion_url": "https://www.notion.so/34df9553c57081daa02ddaaf9fdbc6ad"
    },
    {
      "title": "United Community Banks宣布与Peach State Bancshares签署并购协议",
      "date": "2026-04-21",
      "source": "SEC",
      "category": "金融机构",
      "importance": "中",
      "summary": "美国区域银行并购再现：UCB收购Peach State",
      "impact": "United Community Banks披露将并购Peach State Bancshares，并在交易完成后推动双方银行主体合并。区域/社区银行并购有助于扩张存贷规模与网点覆盖，同时也反映行业在资本与成本约束下的整合趋势；对同业竞争格局与当地存款定价具有边际影响。",
      "targets": "美国区域/社区银行行业、并购整合风险、当地存款与信贷竞争",
      "direction": "中性",
      "keywords": [
        "区域银行",
        "并购",
        "UCB",
        "Peach State",
        "美国银行业"
      ],
      "follow_up": "是",
      "link": "https://www.sec.gov/Archives/edgar/data/857855/000110465926045711/tm2612284d1_8k.htm",
      "notion_url": "https://www.notion.so/34df9553c57081ce8aaac76016e83628"
    },
    {
      "title": "Freeport-McMoRan公布2026年Q1业绩并调整Grasberg Block Cave爬坡节奏",
      "date": "2026-04-23",
      "source": "Freeport-McMoRan",
      "category": "重点公司",
      "importance": "中",
      "summary": "FCX Q1净利8.81亿美元；Grasberg爬坡节奏调整影响全年销量指引",
      "impact": "FCX披露2026年Q1归母净利润8.81亿美元（调整后8.30亿美元），并在高铜价/高金价环境下现金流表现稳健；同时因Grasberg Block Cave地下矿物料处理系统调整，全年铜/金销量指引下调主要反映爬坡时点调整。该信息同时影响铜矿供给预期与矿企成本/资本开支路径，对铜价波动与资源股风险偏好具有参考价值。",
      "targets": "铜/金商品价格预期、铜矿供给与成本曲线、资源股（铜矿/金矿）估值",
      "direction": "中性",
      "keywords": [
        "FCX",
        "铜",
        "黄金",
        "Grasberg",
        "业绩",
        "指引"
      ],
      "follow_up": "是",
      "link": "https://www.sec.gov/Archives/edgar/data/831259/000083125926000021/a1q2026exhibit991.htm",
      "notion_url": "https://www.notion.so/34df9553c570814783baf8ef9bbfaf31"
    }
  ]
}